pdm_winpacker/__init__.py
pdm_winpacker/command.py
pdm_winpacker/winpacker/__init__.py
pdm_winpacker/winpacker/bundler/__init__.py
pdm_winpacker/winpacker/bundler/_system_path.py
pdm_winpacker/winpacker/bundler/bundler.py
pdm_winpacker/winpacker/bundler/command.py
pdm_winpacker/winpacker/bundler/msvcrt/x64/api-ms-win-core-console-l1-1-0.dll
pdm_winpacker/winpacker/bundler/msvcrt/x64/api-ms-win-core-datetime-l1-1-0.dll
pdm_winpacker/winpacker/bundler/msvcrt/x64/api-ms-win-core-debug-l1-1-0.dll
pdm_winpacker/winpacker/bundler/msvcrt/x64/api-ms-win-core-errorhandling-l1-1-0.dll
pdm_winpacker/winpacker/bundler/msvcrt/x64/api-ms-win-core-file-l1-1-0.dll
pdm_winpacker/winpacker/bundler/msvcrt/x64/api-ms-win-core-file-l1-2-0.dll
pdm_winpacker/winpacker/bundler/msvcrt/x64/api-ms-win-core-file-l2-1-0.dll
pdm_winpacker/winpacker/bundler/msvcrt/x64/api-ms-win-core-handle-l1-1-0.dll
pdm_winpacker/winpacker/bundler/msvcrt/x64/api-ms-win-core-heap-l1-1-0.dll
pdm_winpacker/winpacker/bundler/msvcrt/x64/api-ms-win-core-interlocked-l1-1-0.dll
pdm_winpacker/winpacker/bundler/msvcrt/x64/api-ms-win-core-libraryloader-l1-1-0.dll
pdm_winpacker/winpacker/bundler/msvcrt/x64/api-ms-win-core-localization-l1-2-0.dll
pdm_winpacker/winpacker/bundler/msvcrt/x64/api-ms-win-core-memory-l1-1-0.dll
pdm_winpacker/winpacker/bundler/msvcrt/x64/api-ms-win-core-namedpipe-l1-1-0.dll
pdm_winpacker/winpacker/bundler/msvcrt/x64/api-ms-win-core-processenvironment-l1-1-0.dll
pdm_winpacker/winpacker/bundler/msvcrt/x64/api-ms-win-core-processthreads-l1-1-0.dll
pdm_winpacker/winpacker/bundler/msvcrt/x64/api-ms-win-core-processthreads-l1-1-1.dll
pdm_winpacker/winpacker/bundler/msvcrt/x64/api-ms-win-core-profile-l1-1-0.dll
pdm_winpacker/winpacker/bundler/msvcrt/x64/api-ms-win-core-rtlsupport-l1-1-0.dll
pdm_winpacker/winpacker/bundler/msvcrt/x64/api-ms-win-core-string-l1-1-0.dll
pdm_winpacker/winpacker/bundler/msvcrt/x64/api-ms-win-core-synch-l1-1-0.dll
pdm_winpacker-1.0.0.dist-info/entry_points.txt
pdm_winpacker-1.0.0.dist-info/WHEEL
pdm_winpacker-1.0.0.dist-info/METADATA
pdm_winpacker-1.0.0.dist-info/licenses/LICENSE
pdm_winpacker-1.0.0.dist-info/RECORD
