Metadata-Version: 2.1
Name: pdm-winpacker
Version: 1.0.0
Summary: A PDM plugin to bundle python application with python and create a installer using NSIS
License: MIT
Author-email: Samuel Taylor <samtaylor.uk@gmail.com>
Requires-Python: >=3.10
Classifier: Development Status :: 3 - Alpha
Classifier: Programming Language :: Python :: 3
Classifier: Programming Language :: Python :: 3.10
Requires-Dist: installer>=0.6.0
Requires-Dist: pynsist>=2.8
Requires-Dist: unearth>=0.9.0
Project-URL: Homepage, https://github.com/samtayuk/pdm-winpacker
Project-URL: Repository, https://github.com/samtayuk/pdm-winpacker
